image_processing_gabilobbo/__init__.py
image_processing_gabilobbo/processing/__init__.py
image_processing_gabilobbo/processing/combination.py
image_processing_gabilobbo/processing/transformation.py
image_processing_gabilobbo/utils/__init__.py
image_processing_gabilobbo/utils/io.py
image_processing_gabilobbo/utils/plot.py
image_processing_gabilobbo-0.0.1.dist-info/METADATA
image_processing_gabilobbo-0.0.1.dist-info/WHEEL
image_processing_gabilobbo-0.0.1.dist-info/top_level.txt
image_processing_gabilobbo-0.0.1.dist-info/RECORD
