Metadata-Version: 2.1
Name: image_processing_gabilobbo
Version: 0.0.1
Summary: Image Processing Package using Skimage
Home-page: https://github.com/agabilobbo/image-processing-package
Author: Gabriela
Requires-Python: >=3.8
Requires-Dist: matplotlib
Requires-Dist: numpy
Requires-Dist: scikit-image >=0.16.1
